online_policy_adaptation_using_rollout/__init__.py
online_policy_adaptation_using_rollout/__version__.py
online_policy_adaptation_using_rollout/algorithms/__init__.py
online_policy_adaptation_using_rollout/algorithms/policy_iteration_scenario_1.py
online_policy_adaptation_using_rollout/algorithms/rollouts_scenario_1.py
online_policy_adaptation_using_rollout/algorithms/value_iteration_scenario_1.py
online_policy_adaptation_using_rollout/data_collection/__init__.py
online_policy_adaptation_using_rollout/data_collection/data_collection.py
online_policy_adaptation_using_rollout/evaluation/__init__.py
online_policy_adaptation_using_rollout/evaluation/evaluate_scenario_1.py
online_policy_adaptation_using_rollout/evaluation/evaluation.py
online_policy_adaptation_using_rollout/load_generator/__init__.py
online_policy_adaptation_using_rollout/load_generator/async_load_generator.py
online_policy_adaptation_using_rollout/ppo_base_policy/__init__.py
online_policy_adaptation_using_rollout/ppo_base_policy/training_ppo_agent.py
online_policy_adaptation_using_rollout/ppo_base_policy/scenario_1_env/__init__.py
online_policy_adaptation_using_rollout/ppo_base_policy/scenario_1_env/routing_env.py
online_policy_adaptation_using_rollout/ppo_base_policy/scenario_1_env/routing_middle_ware.py
online_policy_adaptation_using_rollout/ppo_base_policy/scenario_2_env/__init__.py
online_policy_adaptation_using_rollout/ppo_base_policy/scenario_2_env/routing_env.py
online_policy_adaptation_using_rollout/ppo_base_policy/scenario_2_env/routing_middle_ware.py
online_policy_adaptation_using_rollout/ppo_base_policy/scenario_3_env/__init__.py
online_policy_adaptation_using_rollout/ppo_base_policy/scenario_3_env/routing_env.py
online_policy_adaptation_using_rollout/ppo_base_policy/scenario_3_env/routing_middle_ware.py
online_policy_adaptation_using_rollout/system_model/__init__.py
online_policy_adaptation_using_rollout/system_model/learning_system_model.py
online_policy_adaptation_using_rollout-1.0.0.dist-info/METADATA
online_policy_adaptation_using_rollout-1.0.0.dist-info/WHEEL
online_policy_adaptation_using_rollout-1.0.0.dist-info/top_level.txt
online_policy_adaptation_using_rollout-1.0.0.dist-info/RECORD
